Workbook

Sheet Executive Summary
B4: APPLE INC VALUATION ANALYSIS
T5: EXECUTIVE SUMMARY
B6: DCF & Relative Valuation Project | T6: This project aims to estimate the intrinsic value of Apple Inc. using both Discounted Cash Flow (DCF) and Relative Valuation approaches. The objective is to evaluate whether Apple’s current market price accurately reflects the company’s underlying financial performance and long-term growth potential. The DCF valuation model was developed by projecting Apple’s future revenues, operating profits, and free cash flows over a five-year forecast period. Key assumptions were made regarding revenue growth, operating margins, tax rates, capital expenditures, and working capital requirements. These projected cash flows were discounted using the company’s Weighted Average Cost of Capital (WACC) to determine their present value. A terminal value was also calculated to capture the value of cash flows beyond the forecast period, reflecting the company’s long-term sustainable growth. The DCF analysis produced an estimated intrinsic share value significantly below Apple’s current market price, suggesting that the stock may be trading at a premium relative to its fundamental cash flow valuation. Sensitivity analysis was conducted to evaluate how changes in key assumptions such as WACC and terminal growth rate impact the valuation results, highlighting the importance of these parameters in long-term valuation models. To complement the intrinsic valuation approach, a Comparable Company Analysis was performed using key valuation multiples including EV/Revenue, EV/EBITDA, Price-to-Earnings (P/E), and Price-to-Book (P/B). Apple was compared with major technology peers such as Microsoft, Alphabet, and Meta to estimate its value based on prevailing market multiples. The results from relative valuation produced a target price range closer to the current market price, though still indicating that the stock may be somewhat overvalued relative to peer benchmarks. Overall, the combined valuation approaches provide a comprehensive assessment of Apple’s financial value and market positioning. While the DCF model offers a conservative estimate based on projected cash flows, the relative valuation reflects current market sentiment and industry benchmarks. Together, these methods provide a balanced framework for evaluating Apple’s valuation and supporting informed investment analysis.
B7: Companies Compared: Apple Inc | Microsoft | Alphabet | Meta Benchmark : Technology Sector
B9: VALUATION SUMMARY | K9: RELATIVE VALUATION - COMPARABLES COMPANY METHOD
B12: METRIC | F12: VALUE
B13: Enterprise Value | F13: $1.55T
B14: Equity Value | F14: $1.49T
B15: Intrinsic Price (DCF) | F15: 101.5
B16: Relative Target Price | F16: 209.71
B17: Current Market Price | F17: 250.12
B18: Upside / Downside | F18: -0.16
B19: Valuation Signal | F19: Overvalued
B22: FCFF FORECAST | K22: ENTERPRISE VALUE BREAKDOWN
B40: DCF Sensitivity (WACC vs Growth) | K40: RELATIVE VALUATION SUMMARY
B43: WACC / TV (Growth Rate) | C43: 0.02 | D43: 0.025 | E43: 0.03 | L43: Method | M43: Implied Price | N43: Current Price | O43: Scenario | P43: Conclusion
B44: 0.09 | C44: 112.84265 | D44: 119.92722 | E44: 128.19256 | L44: EV/Revenue | M44: 258 | N44: 250.12 | O44: IP > CP | P44: Undervalued
B45: 0.1 | C45: 98.703512 | D45: 103.88326 | E45: 109.80298 | L45: EV/EBITDA | M45: 206 | N45: =N44 -> 250.12 | O45: IP < CP | P45: Overvalued
B46: 0.11 | C46: 87.865242 | D46: 91.78336 | E46: 96.191244 | L46: P/E | M46: 213 | N46: =N45 -> 250.12 | O46: =O45 -> IP < CP | P46: Overvalued
L47: P/B | M47: 48 | N47: =N46 -> 250.12 | O47: =O46 -> IP < CP | P47: =P46 -> Overvalued
B50: FOOTBALL FIELD ANALYSIS | K50: KEY INSIGHTS
K54: • Apple generates strong and stable cash flows • Terminal value accounts for majority of DCF valuation • Relative valuation indicates smaller downside than DCF • Market price reflects optimistic growth expectations

Sheet AAPL Financial Data
B2: Financial Data from Stock Analysis | J2: Purpose of the Sheet
B3: Income Statement | J3: This sheet collects historical financial statement data for Apple (AAPL) from the Income Statement and Balance Sheet & Cash Flow Statement. The goal is to build a reliable financial base that will be used in later sheets to estimate cash flows, cost of capital, and company valuation. In a DCF valuation, everything starts with historical financial performance, because future projections are usually based on past trends. Historical data shows how the company has performed over time. Example insights: • Revenue growth trends • Profitability (EBIT margin) • Investment intensity (CapEx) • Operating efficiency This helps determine whether the company is growing, stable, or declining. DCF valuation relies on future free cash flows. Those cash flows are estimated using historical trends in: • Revenue growth • Operating margins • Capital investments • Working capital changes So this sheet provides the foundation for forecasting. The data from this sheet feeds directly into the next step of valuation, which is: FCFF Calculation
B4: Year | C4: 2025 | D4: 2024 | E4: 2023 | F4: 2022 | G4: 2021
B6: Revenue | C6: 416161 | D6: 391035 | E6: 383285 | F6: 394328 | G6: 365817
B7: Operating Income (EBIT) | C7: 133050 | D7: 123216 | E7: 114301 | F7: 119437 | G7: 108949
B8: Pre Tax Expense | C8: 132729 | D8: 123485 | E8: 113736 | F8: 119103 | G8: 109217
B9: Income Tax Expense | C9: 20719 | D9: 29749 | E9: 16741 | F9: 19300 | G9: 14527
B10: Net Income | C10: 112010 | D10: 93736 | E10: 96995 | F10: 99803 | G10: 94680
B12: Cash Flow Statement
B14: Depreciation & Amortization | C14: 11698 | D14: 11445 | E14: 11519 | F14: 11104 | G14: 11284
B15: Captial Expenditures (CapEx) | C15: -12715 | D15: -9447 | E15: -10959 | F15: -10708 | G15: -11085
B17: Balance Sheet Data
B19: Current Assets | C19: 147957 | D19: 152987 | E19: 143566 | F19: 135405 | G19: 134836
B20: Current Liabilities | C20: 165631 | D20: 176392 | E20: 145308 | F20: 153982 | G20: 125481
B21: Cash & Cash Equivalents | C21: 35934 | D21: 29943 | E21: 29965 | F21: 23646 | G21: 34940
B22: Total Debt | C22: 98657 | D22: 106629 | E22: 111088 | F22: 120069 | G22: 124719
B24: Market Data Current Values
B26: Share Price | C26: 275
B27: Shares Outstanding | C27: 14680
B28: Market Cap | C28: 3670000 | J28: Interpretation
B29: Enterprise Value | C29: 3620000 | J29: The Financial Data sheet compiles historical income statement and balance sheet data for Apple Inc. to establish the financial foundation required for valuation. Key variables such as revenue, EBIT, depreciation, capital expenditures, and working capital are extracted to analyze operating performance and capital investment trends. These metrics enable the calculation of operating profitability and provide the inputs necessary for estimating Free Cash Flow to the Firm (FCFF) in subsequent sheets. By analyzing historical financial data, the model ensures that future projections and valuation estimates are grounded in the company’s actual financial performance.

Sheet AAPL FCFF Calculation
B2: FCFF Calculation for AAPL Data
B4: Year | C4: 2025 | D4: 2024 | E4: 2023 | F4: 2022 | G4: 2021 | K4: Purpose of the Sheet
K5: This sheet calculates Free Cash Flow to the Firm (FCFF), which represents the cash generated by the company that is available to all capital providers (both debt holders and equity shareholders). FCFF is the core input of the DCF valuation model, because the DCF method values a company by estimating the present value of future free cash flows. FCFF shows how much real cash the company generates from operations after reinvesting in the business. It answers an important question: How much cash does the company produce that can be used to repay debt, pay dividends, or reinvest? Components Explained: 1) EBIT (Earnings Before Interest and Taxes) Represents operating profit generated by the company before financing costs. 2) EBIT(1 − Tax) Converts operating profit into after-tax operating income. This reflects the profit the company would earn if it had no debt. 3) Depreciation & Amortization Depreciation is added back because: It reduces accounting profit But does not involve an actual cash outflow Therefore it must be added back to calculate real cash flow. 4) Capital Expenditure (CapEx) CapEx represents investments in: • Property • Equipment • Technology • Infrastructure These investments are cash outflows, so they are subtracted from FCFF. 5) Change in Working Capital Working capital includes items like: • Inventory • Receivables • Payables If working capital increases, the company uses cash, so it reduces FCFF. If working capital decreases, it frees up cash.
B6: Tax Rate Calculation
B7: Pre Tax Expense | C7: 132729 | D7: 123485 | E7: 113736 | F7: 119103 | G7: 109217
B8: Income Tax Expense | C8: 20719 | D8: 29749 | E8: 16741 | F8: 19300 | G8: 14527
B9: Tax Rate | C9: =C8/C7 -> 0.15610002 | D9: =D8/D7 -> 0.24091185 | E9: =E8/E7 -> 0.14719174 | F9: =F8/F7 -> 0.16204462 | G9: =G8/G7 -> 0.13301043
B11: NOPAT Calculation
B12: EBIT | C12: 133050 | D12: 123216 | E12: 114301 | F12: 119437 | G12: 108949
B13: NOPAT | C13: =C12*(1-C9) -> 112280.89 | D13: =D12*(1-D9) -> 93531.805 | E13: =E12*(1-E9) -> 97476.837 | F13: =F12*(1-F9) -> 100082.88 | G13: =G12*(1-G9) -> 94457.647
B15: Working Capital Calculaiton
B16: Current Assets | C16: 147957 | D16: 152987 | E16: 143566 | F16: 135405 | G16: 134836
B17: Current Liabilities | C17: 165631 | D17: 176392 | E17: 145308 | F17: 153982 | G17: 125481
B18: Working Capital | C18: =C16-C17 -> -17674 | D18: =D16-D17 -> -23405 | E18: =E16-E17 -> -1742 | F18: =F16-F17 -> -18577 | G18: =G16-G17 -> 9355
B19: Δ Working Capital | C19: =C18-(D18) -> 5731 | D19: =D18-(E18) -> -21663 | E19: =E18-(F18) -> 16835 | F19: =F18-(G18) -> -27932
B21: FCFF Calculation
B22: Depreciation & Amortization | C22: 11698 | D22: 11445 | E22: 11519 | F22: 11104 | G22: 11284
B23: Captial Expenditures (CapEx) | C23: -12715 | D23: -9447 | E23: -10959 | F23: -10708 | G23: -11085
B24: FCFF | C24: =C13+C22+(C23)-(C19) -> 105532.89 | D24: =D13+D22+(D23)-(D19) -> 117192.81 | E24: =E13+E22+(E23)-(E19) -> 81201.837 | F24: =F13+F22+(F23)-(F19) -> 128410.88
B26: Interpretation
B27: The FCFF Calculation sheet estimates the Free Cash Flow to the Firm generated by Apple Inc. Free Cash Flow to the Firm represents the cash available to all providers of capital after accounting for operating expenses, taxes, and necessary reinvestments in the business. The calculation begins with EBIT adjusted for taxes to obtain after-tax operating profit, then adds back non-cash expenses such as depreciation. Capital expenditures and changes in working capital are deducted to reflect the cash required to sustain and grow operations. This measure provides a more accurate representation of the company’s true cash-generating ability and serves as the primary input for the Discounted Cash Flow valuation model used in subsequent sheets.

Sheet AAPL WACC Calculation
B2: WACC Calulcation for the Use in DCF - FCFF Model
B4: Data For WACC Calculation | E4: Interpretation
B5: Risk Free Rate (Rf) | C5: 0.042 | E5: The WACC Calculation sheet determines the Weighted Average Cost of Capital for Apple Inc., which represents the average rate of return required by both equity investors and debt holders. The cost of equity is estimated using the Capital Asset Pricing Model (CAPM), incorporating the risk-free rate, market risk premium, and the company’s beta to capture systematic market risk. The cost of debt is derived from the company’s borrowing costs and adjusted for the tax shield benefit of interest expenses. These costs are weighted according to the firm’s capital structure to obtain the WACC. This rate serves as the discount factor in the DCF model, allowing future free cash flows to be converted into present value and enabling the estimation of the company’s enterprise value.
B6: Beta (5Y) | C6: 1.12
B7: Market Risk Premium (Assumed) | C7: 0.055
B8: Market Value of Equity | C8: ='AAPL Financial Data'!C28 -> 3670000
B9: Market Value of Debt | C9: ='AAPL Financial Data'!C22 -> 98657
B11: Cost of Debt | C11: 0.04
B12: Weight of Debt | C12: =C9/(C8+C9) -> 0.026178291
B14: Risk Free Rate (Rf) | C14: 0.042
B15: Beta (5Y) | C15: 1.12
B16: Market Risk Premium (Assumed) | C16: 0.055
B17: Cost of Equity | C17: =C14+C15*(C16) -> 0.1036
B18: Weight of Equity | C18: =C8/(C8+C9) -> 0.97382171
B20: Normalized Tax Rate (Assumed) | C20: 0.16
B22: WACC | C22: =(C17*C18)+(C11*C12*(1-C20)) -> 0.10176752
B25: Purpose of the Sheet
B26: This sheet calculates the Weighted Average Cost of Capital (WACC), which represents the minimum return required by investors for investing in the company. In the DCF model, WACC is used as the discount rate to convert future cash flows into their present value. It reflects the overall cost of financing the company, considering both: • Equity financing (shareholders) • Debt financing (lenders) Cost of Equity (Re) Cost of equity represents the return expected by shareholders for investing in the company’s stock. It is calculated using the Capital Asset Pricing Model (CAPM): Rf + Beta*(Rm-Rf) Cost of Debt (Rd) Cost of debt represents the interest rate the company pays on its borrowings. It is often calculated as: Interest Expense / Total Debt Because interest is tax deductible, the effective cost of debt becomes: Rd*(1-Tax Rate). This adjustment reflects the tax shield benefit of debt financing.
B47: Note:
B48: For large investment-grade companies like Apple, analysts normally do not calculate cost of debt manually. Instead they use the yield on the company’s bonds or a rounded estimate. Apple’s recent bond yields are roughly 3.5%–4.2%. But if it is to be calculated Cost of Debt = Interest Expense / Total Debt

Sheet AAPL DCF Valuation
B2: DCF Valuation - FCFF for Apple Inc
B4: DCF Valuation Table | K4: Assumption Table for AAPL | O4: DCF Valuation Model - Interpretation
C5: 0 | D5: 1 | E5: 2 | F5: 3 | G5: 4 | H5: 5 | I5: TV | K5: Variable | L5: Assumption | O5: This sheet presents the complete Discounted Cash Flow (DCF) valuation for Apple Inc. using the Free Cash Flow to the Firm (FCFF) approach. The purpose of this model is to estimate the intrinsic value of Apple by forecasting its future cash flows and discounting them to present value using the company’s Weighted Average Cost of Capital (WACC). The model begins with revenue projections for the next five years based on an assumed annual revenue growth rate of 5%, reflecting stable long-term growth for a mature technology company. Operating profitability is captured using an EBIT margin assumption of 30%, which is consistent with Apple’s historical margins. After applying the tax rate of 16%, Net Operating Profit After Tax (NOPAT) is calculated to measure operating profit available to all capital providers. To convert accounting profits into actual cash flows, adjustments are made for non-cash expenses and reinvestment needs. Depreciation is added back, while capital expenditures and changes in working capital are deducted, resulting in the calculation of Free Cash Flow to the Firm (FCFF) for each forecast year. These projected cash flows are then discounted using the company’s WACC of 10.18%, which reflects the overall required return demanded by both equity investors and debt holders. Since companies are assumed to operate indefinitely, a terminal value is calculated using a perpetual growth rate of 2.5%, representing long-term sustainable economic growth. The terminal value captures the value of cash flows beyond the explicit forecast period. By summing the present value of projected FCFF and the discounted terminal value, the model estimates an Enterprise Value of approximately $1.55 trillion. After adjusting for net debt, the resulting Equity Value is approximately $1.49 trillion. Dividing this value by the total number of shares outstanding results in an intrinsic share price estimate of $101.50. When compared with the current market price of $275, the model indicates that Apple’s stock appears overvalued by approximately 63%, suggesting that the market price is significantly higher than the intrinsic value estimated by the DCF model. This difference may reflect optimistic market expectations regarding future growth, innovation, or strategic expansion that are not fully captured in the model assumptions. Overall, the DCF valuation provides a structured framework for estimating Apple’s intrinsic value based on its projected ability to generate cash flows, offering investors a long-term perspective on the company’s fundamental valuation
B6: Year | C6: 2025A | D6: 2026F | E6: 2027F | F6: 2028F | G6: 2029F | H6: 2030F | K6: Revenue Growth | L6: 0.05
B7: Growth Rate | C7: =('AAPL Financial Data'!C6-'AAPL Financial Data'!D6)/'AAPL Financial Data'!D6 -> 0.064255118 | D7: 0.05 | E7: 0.05 | F7: 0.05 | G7: 0.05 | H7: 0.05 | I7: 0.025 | K7: EBIT Margin | L7: 0.3
B8: Revenue | C8: 416161 | D8: =C8*(1+D7) -> 436969.05 | E8: =D8*(1+E7) -> 458817.5 | F8: =E8*(1+F7) -> 481758.38 | G8: =F8*(1+G7) -> 505846.3 | H8: =G8*(1+H7) -> 531138.61 | K8: Tax Rate | L8: 0.16
B9: EBIT Margin | C9: =C10/C8 -> 0.319708 | D9: 0.3 | E9: 0.3 | F9: 0.3 | G9: 0.3 | H9: 0.3 | K9: Depreciation | L9: 0.03 | M9: of Revenue
B10: EBIT | C10: ='AAPL FCFF Calculation'!C12 -> 133050 | D10: =D8*D9 -> 131090.71 | E10: =E8*E9 -> 137645.25 | F10: =F8*F9 -> 144527.51 | G10: =G8*G9 -> 151753.89 | H10: =H8*H9 -> 159341.58 | K10: CapEx | L10: 0.03 | M10: of Revenue
B11: Tax Rate | C11: ='AAPL FCFF Calculation'!C9 -> 0.15610002 | D11: =L8 -> 0.16 | E11: =D11 -> 0.16 | F11: =E11 -> 0.16 | G11: =F11 -> 0.16 | H11: =G11 -> 0.16 | K11: ΔWC | L11: 0.01 | M11: of Revenue Change
B12: NOPAT | C12: ='AAPL FCFF Calculation'!C13 -> 112280.89 | D12: =D10*(1-D11) -> 110116.2 | E12: =E10*(1-E11) -> 115622.01 | F12: =F10*(1-F11) -> 121403.11 | G12: =G10*(1-G11) -> 127473.27 | H12: =H10*(1-H11) -> 133846.93
B13: Depreciation | C13: ='AAPL FCFF Calculation'!C22 -> 11698 | D13: =$L$9*D8 -> 13109.072 | E13: =$L$9*E8 -> 13764.525 | F13: =$L$9*F8 -> 14452.751 | G13: =$L$9*G8 -> 15175.389 | H13: =$L$9*H8 -> 15934.158 | K13: WACC Calculated | L13: ='AAPL WACC Calculation'!C22 -> 0.10176752
B14: CapEx | C14: 12715 | D14: =$L$10*D8 -> 13109.072 | E14: =$L$10*E8 -> 13764.525 | F14: =$L$10*F8 -> 14452.751 | G14: =$L$10*G8 -> 15175.389 | H14: =$L$10*H8 -> 15934.158
B15: Δ in Revenue | D15: =D8-C8 -> 20808.05 | E15: =E8-D8 -> 21848.453 | F15: =F8-E8 -> 22940.875 | G15: =G8-F8 -> 24087.919 | H15: =H8-G8 -> 25292.315
B16: Δ Working Capital | D16: =$L$11*D15 -> 208.0805 | E16: =$L$11*E15 -> 218.48453 | F16: =$L$11*F15 -> 229.40875 | G16: =$L$11*G15 -> 240.87919 | H16: =$L$11*H15 -> 252.92315
B17: FCFF | D17: =D12+D13-D14-D16 -> 109908.12 | E17: =E12+E13-E14-E16 -> 115403.53 | F17: =F12+F13-F14-F16 -> 121173.7 | G17: =G12+G13-G14-G16 -> 127232.39 | H17: =H12+H13-H14-H16 -> 133594.01
B18: TV | I18: =H17*(1+I7)/('AAPL WACC Calculation'!C22-'AAPL DCF Valuation'!I7) -> 1783747.3
B19: PV (FCFF) | D19: =D17/(1+$L$13)^D5 -> 99756.181 | E19: =E17/(1+$L$13)^E5 -> 95069.049 | F19: =F17/(1+$L$13)^F5 -> 90602.146 | G19: =G17/(1+$L$13)^G5 -> 86345.124 | H19: =H17/(1+$L$13)^H5 -> 82288.122 | I19: =SUM(D19:H19) -> 454060.62
B20: PV (TV) | I20: =I18/(1+L13)^H5 -> 1098711.1
B21: Enterprise Value | I21: =SUM(D19:H19)+I20 -> 1552771.7
B22: Total Debt | I22: ='AAPL Financial Data'!C22 -> 98657
B23: Cash | I23: ='AAPL Financial Data'!C21 -> 35934
B24: Net Debt | I24: =I22-I23 -> 62723
B25: Equity Value | I25: =I21-I24 -> 1490048.7
B26: Number of Shares Outstanding | I26: ='AAPL Financial Data'!C27 -> 14680
B27: Value per Share | I27: =I25/I26 -> 101.50196
B29: Metric | C29: Value
B30: Enterprise Value | C30: 1.55 | D30: Trillion
B31: Equity Value | C31: 1.49 | D31: Trillion
B32: Intrinsic Share Price | C32: 101.5
B33: Current Market Price | C33: 275
B34: Upside / Downslude | C34: =(C32-C33)/C33 -> -0.63090909
B35: Valuation Signal | C35: Over Valued
B37: FCFF Forecast Chart | K37: Enterprise Value Breakdown Chart
B38: Year | C38: FCFF | K38: Component | L38: Value | M38: Percentage of Total
B39: 2026 | C39: =D17 -> 109908.12 | K39: PV of FCFF | L39: =I19 -> 454060.62 | M39: =L39/(L39+L40) -> 0.29241943
B40: 2027 | C40: =E17 -> 115403.53 | K40: PV of Terminal Value | L40: =I20 -> 1098711.1 | M40: =1-M39 -> 0.70758057
B41: 2028 | C41: =F17 -> 121173.7
B42: 2029 | C42: =G17 -> 127232.39
B43: 2030 | C43: =H17 -> 133594.01
D45: The chart illustrates the projected growth in Apple’s Free Cash Flow to the Firm (FCFF) over the forecast period. The steady increase reflects stable revenue growth assumptions and consistent operating margins, indicating strong and predictable cash generation capacity. | N45: The enterprise value breakdown chart illustrates the contribution of forecast free cash flows and terminal value to Apple’s overall valuation. The results show that a significant portion of the company’s value is derived from the terminal value, which captures the present value of cash flows beyond the explicit forecast period. This highlights the importance of long-term growth assumptions in DCF valuation models.

Sheet Sensitivity Analysis
B2: Sensitivity Analysis of DCF Valuation
B4: Data required for Sensitivity Analysis | H4: Sensitivity Analysis - Interpretation
B5: FCFF (Y5) | C5: ='AAPL DCF Valuation'!H17 -> 133594.01 | H5: The sensitivity analysis sheet evaluates how changes in key valuation assumptions affect the estimated value of Apple Inc. in the DCF model. Since valuation outcomes are highly dependent on assumptions, particularly the Weighted Average Cost of Capital (WACC) and the terminal growth rate, this analysis helps assess the robustness of the valuation results. In this model, the sensitivity analysis examines different combinations of WACC ranging from 9% to 11% and terminal growth rates ranging from 2% to 3%. These variables are critical because they directly influence the terminal value and the present value of future cash flows. Even small changes in these assumptions can significantly impact the final valuation. The analysis first recalculates the Terminal Value (TV) for each combination of WACC and growth rate. Since terminal value typically represents a large portion of total firm value in a DCF model, changes in these inputs can lead to substantial variation in valuation outcomes. The model then computes the present value of the terminal value, followed by updated estimates of Enterprise Value, Equity Value, and finally the intrinsic share price. The results show that Apple’s estimated intrinsic value per share varies between approximately $88 in the bear-case scenario (higher WACC and lower growth) and $128 in the bull-case scenario (lower WACC and higher growth). The base-case estimate of approximately $104 per share reflects the model’s central assumptions of a 10% WACC and 2.5% terminal growth rate. This range illustrates the degree of uncertainty inherent in valuation models and highlights how sensitive the company’s valuation is to discount rates and long-term growth expectations. Sensitivity analysis therefore provides investors with a valuation range rather than a single point estimate, enabling better assessment of risk and potential upside or downside. Overall, the analysis confirms that while the intrinsic value varies across different scenarios, the estimated valuation remains significantly below the current market price, reinforcing the conclusion that the stock appears overvalued under the assumptions used in this model.
B6: Sum of PV(FCFF) | C6: ='AAPL DCF Valuation'!I19 -> 454060.62
B7: Net Debt | C7: ='AAPL DCF Valuation'!I24 -> 62723
B8: Number of Shares Outstnding | C8: ='AAPL DCF Valuation'!I26 -> 14680
B10: Sensitivity Analysis of TV
B11: WACC / TV (Growth Rate) | C11: 0.02 | D11: 0.025 | E11: 0.03
B12: 0.09 | C12: =$C$5*(1+$C$11)/(B12-$C$11) -> 1946655.5 | D12: =$C$5*(1+$D$11)/(B12-$D$11) -> 2106674.7 | E12: =$C$5*(1+$E$11)/(B12-$E$11) -> 2293363.8
B13: 0.1 | C13: =$C$5*(1+$C$11)/(B13-$C$11) -> 1703323.6 | D13: =$C$5*(1+$D$11)/(B13-$D$11) -> 1825784.8 | E13: =$C$5*(1+$E$11)/(B13-$E$11) -> 1965740.4
B14: 0.11 | C14: =$C$5*(1+$C$11)/(B14-$C$11) -> 1514065.4 | D14: =$C$5*(1+$D$11)/(B14-$D$11) -> 1610986.6 | E14: =$C$5*(1+$E$11)/(B14-$E$11) -> 1720022.8
B16: Sensitivity Analysis of PV(TV)
B17: WACC / TV (Growth Rate) | C17: 0.02 | D17: 0.025 | E17: 0.03
B18: 0.09 | C18: =C12/(1+$B$18)^5 -> 1265192.5 | D18: =D12/(1+$B$18)^5 -> 1369194 | E18: =E12/(1+$B$18)^5 -> 1490529.1
B19: 0.1 | C19: =C13/(1+$B$19)^5 -> 1057629.9 | D19: =D13/(1+$B$19)^5 -> 1133668.7 | E19: =E13/(1+$B$19)^5 -> 1220570.1
B20: 0.11 | C20: =C14/(1+$B$20)^5 -> 898524.13 | D20: =D14/(1+$B$20)^5 -> 956042.11 | E20: =E14/(1+$B$20)^5 -> 1020749.8
B22: Sensitivity Analysis of Enterprise Value
B23: WACC / TV (Growth Rate) | C23: 0.02 | D23: 0.025 | E23: 0.03
B24: 0.09 | C24: =C18+$C$6 -> 1719253.1 | D24: =D18+$C$6 -> 1823254.6 | E24: =E18+$C$6 -> 1944589.7
B25: 0.1 | C25: =C19+$C$6 -> 1511690.6 | D25: =D19+$C$6 -> 1587729.3 | E25: =E19+$C$6 -> 1674630.7
B26: 0.11 | C26: =C20+$C$6 -> 1352584.8 | D26: =D20+$C$6 -> 1410102.7 | E26: =E20+$C$6 -> 1474810.5
B28: Sensitivity Analysis of Equity Value
B29: WACC / TV (Growth Rate) | C29: 0.02 | D29: 0.025 | E29: 0.03
B30: 0.09 | C30: =C24-$C$7 -> 1656530.1 | D30: =D24-$C$7 -> 1760531.6 | E30: =E24-$C$7 -> 1881866.7
B31: 0.1 | C31: =C25-$C$7 -> 1448967.6 | D31: =D25-$C$7 -> 1525006.3 | E31: =E25-$C$7 -> 1611907.7
B32: 0.11 | C32: =C26-$C$7 -> 1289861.8 | D32: =D26-$C$7 -> 1347379.7 | E32: =E26-$C$7 -> 1412087.5 | H32: DCF Sensitivity Heatmap - WACC vs Terminal Growth
H33: WACC / TV (Growth Rate) | I33: 0.02 | J33: 0.025 | K33: 0.03
B34: Sensitivity Analysis of Value Per Share (Intrinsic Value) | H34: 0.09 | I34: =C36 -> 112.84265 | J34: =D36 -> 119.92722 | K34: =E36 -> 128.19256
B35: WACC / TV (Growth Rate) | C35: 0.02 | D35: 0.025 | E35: 0.03 | H35: 0.1 | I35: =C37 -> 98.703512 | J35: =D37 -> 103.88326 | K35: =E37 -> 109.80298
B36: 0.09 | C36: =C30/$C$8 -> 112.84265 | D36: =D30/$C$8 -> 119.92722 | E36: =E30/$C$8 -> 128.19256 | H36: 0.11 | I36: =C38 -> 87.865242 | J36: =D38 -> 91.78336 | K36: =E38 -> 96.191244
B37: 0.1 | C37: =C31/$C$8 -> 98.703512 | D37: =D31/$C$8 -> 103.88326 | E37: =E31/$C$8 -> 109.80298
B38: 0.11 | C38: =C32/$C$8 -> 87.865242 | D38: =D32/$C$8 -> 91.78336 | E38: =E32/$C$8 -> 96.191244 | H38: The sensitivity analysis illustrates how Apple’s intrinsic valuation changes with variations in the discount rate (WACC) and terminal growth rate assumptions. The heatmap highlights that higher growth assumptions and lower discount rates significantly increase the estimated share price, while higher discount rates reduce valuation. This analysis helps assess the robustness of the DCF model and provides a range of potential valuations under different economic scenarios. Example insight: • Lower WACC → Higher company value • Higher growth → Higher company value This helps investors understand valuation uncertainty.
B40: Valuation Range
B41: Scenario | C41: Value
B42: Bear Case | C42: =C38 -> 87.865242
B43: Base Case | C43: =D37 -> 103.88326
B44: Bull Case | C44: =E36 -> 128.19256

Sheet Relative Valuation
B2: Relative Valuation - Comparable Companies Method
B4: Company Data | E4: Market Data | O4: Financials | T4: Valuation
B5: Company Name | C5: Ticker | E5: Share Price | F5: Shares Outstanding | G5: Equity Value | H5: Total Debt | I5: Cash & Cash Equivalents | J5: Net Debt | K5: Enterprise Value | L5: Book Value | M5: Book Value Per Share | O5: Revenue | P5: EBITDA | Q5: Net Income | R5: EPS | T5: EV/ Revenue | U5: P/B | V5: P/E | W5: EV/ EBITDA
B6: Apple | C6: AAPL | E6: 250.12 | F6: 14920 | G6: =E6*F6 -> 3731790.4 | H6: 90509 | I6: 45317 | J6: =H6-I6 -> 45192 | K6: =G6+J6 -> 3776982.4 | L6: 88190 | M6: =L6/F6 -> 5.9108579 | O6: 435617 | P6: 152902 | Q6: 117777 | R6: 7.91 | T6: =K6/O6 -> 8.6704201 | U6: =E6/M6 -> 42.315346 | V6: =E6/R6 -> 31.620733 | W6: =K6/P6 -> 24.701982
B7: Alphabet | C7: GOOG | E7: 301.46 | F7: 12230 | G7: =E7*F7 -> 3686855.8 | H7: 59291 | I7: 30708 | J7: =H7-I7 -> 28583 | K7: =G7+J7 -> 3715438.8 | L7: 415265 | M7: =L7/F7 -> 33.95462 | O7: 402836 | P7: 150175 | Q7: 132170 | R7: 10.82 | T7: =K7/O7 -> 9.2232045 | U7: =G7/L7 -> 8.8783206 | V7: =E7/R7 -> 27.861368 | W7: =K7/P7 -> 24.740728
B8: Microsoft | C8: MSFT | E8: 395.55 | F8: 7462 | G8: =E8*F8 -> 2951594.1 | H8: 57607 | I8: 24296 | J8: =H8-I8 -> 33311 | K8: =G8+J8 -> 2984905.1 | L8: 390875 | M8: =L8/F8 -> 52.382069 | O8: 305453 | P8: 184761 | Q8: 119262 | R8: 15.99 | T8: =K8/O8 -> 9.7720602 | U8: =G8/L8 -> 7.5512481 | V8: =E8/R8 -> 24.737336 | W8: =K8/P8 -> 16.155493
B9: Meta | C9: META | E9: 613.71 | F9: 2574 | G9: =E9*F9 -> 1579689.5 | H9: 83897 | I9: 35873 | J9: =H9-I9 -> 48024 | K9: =G9+J9 -> 1627713.5 | L9: 217243 | M9: =L9/F9 -> 84.39899 | O9: 200966 | P9: 101892 | Q9: 60458 | R9: 23.49 | T9: =K9/O9 -> 8.0994474 | U9: =E9/M9 -> 7.2715325 | V9: =E9/R9 -> 26.126437 | W9: =K9/P9 -> 15.97489
B12: Statistic | T12: EV/ Revenue | U12: P/B | V12: P/E | W12: EV/ EBITDA
B13: High | T13: =MAX(T6:T9) -> 9.7720602 | U13: =MAX(U6:U9) -> 42.315346 | V13: =MAX(V6:V9) -> 31.620733 | W13: =MAX(W6:W9) -> 24.740728
B14: 75th Percentile | T14: =_xlfn.PERCENTILE.INC(T6:T9,0.75) -> 9.3604184 | U14: =_xlfn.PERCENTILE.INC(U6:U9,0.75) -> 17.237577 | V14: =_xlfn.PERCENTILE.INC(V6:V9,0.75) -> 28.801209 | W14: =_xlfn.PERCENTILE.INC(W6:W9,0.75) -> 24.711668
B15: Average | T15: =AVERAGE(T6:T9) -> 8.941283 | U15: =AVERAGE(U6:U9) -> 16.504112 | V15: =AVERAGE(V6:V9) -> 27.586468 | W15: =AVERAGE(W6:W9) -> 20.393273
B16: Median | T16: =MEDIAN(T6:T9) -> 8.9468123 | U16: =MEDIAN(U6:U9) -> 8.2147843 | V16: =MEDIAN(V6:V9) -> 26.993902 | W16: =MEDIAN(W6:W9) -> 20.428737
B17: 25th Percentile | T17: =_xlfn.PERCENTILE.INC(T6:T9,0.25) -> 8.5276769 | U17: =_xlfn.PERCENTILE.INC(U6:U9,0.25) -> 7.4813192 | V17: =_xlfn.PERCENTILE.INC(V6:V9,0.25) -> 25.779162 | W17: =_xlfn.PERCENTILE.INC(W6:W9,0.25) -> 16.110343
B18: Minimum | T18: =MIN(T6:T9) -> 8.0994474 | U18: =MIN(U6:U9) -> 7.2715325 | V18: =MIN(V6:V9) -> 24.737336 | W18: =MIN(W6:W9) -> 15.97489
B21: Compareable Valuation of Apple Inc | L21: Relatve Valuation - Comparable Companies Method - Interpretation
B22: Method | C22: Implied Enterprise Value | D22: Net Debt | E22: Implied Equity Value | F22: Shares Outstanding | G22: Implied Share Price | H22: Share Price | I22: Scenario | J22: Reccomendation | L22: The relative valuation sheet estimates the value of Apple Inc. using the Comparable Companies Method, which determines a firm’s value by comparing it with similar companies in the same industry. Instead of forecasting cash flows like the DCF model, this approach relies on market multiples derived from peer companies to estimate the company’s fair value For this analysis, Apple is compared with major technology peers including Alphabet, Microsoft, and Meta, which operate in similar digital and technology-driven markets. Market data such as share price, shares outstanding, total debt, cash balances, and enterprise value were collected for each company. Financial metrics including revenue, EBITDA, net income, and earnings per share were then used to compute valuation multiples. The key multiples analyzed include EV/Revenue, EV/EBITDA, Price-to-Earnings (P/E), and Price-to-Book (P/B). These multiples capture different aspects of company valuation. EV/Revenue measures how the market values the company relative to its sales, EV/EBITDA reflects operating profitability before financing and accounting effects, P/E evaluates valuation relative to earnings, and P/B compares the company’s market value with its accounting book value. The average and median multiples derived from the peer group are then applied to Apple’s financial metrics to estimate its implied enterprise value and equity value. This results in implied share prices based on each valuation method. The analysis indicates implied share prices of approximately $258.19 using EV/Revenue, $206.33 using EV/EBITDA, $48.56 using P/B, and $213.09 using P/E. Since some multiples may be less reliable for technology companies, particularly Price-to-Book, greater emphasis is placed on EV/EBITDA and P/E ratios, which better reflect operating profitability and earnings power. Based on these more relevant multiples, Apple’s estimated target price range falls between approximately $206 and $213, with a base target price of around $209.71 per share. When compared to the current market price of approximately $250.12, the analysis suggests a potential downside of around 16%, indicating that Apple’s stock may currently be overvalued relative to its industry peers. This conclusion aligns with the results from the DCF valuation, providing additional support for the assessment that the stock price may be trading above its intrinsic value under current assumptions. Overall, the relative valuation approach complements the DCF analysis by incorporating market-based benchmarks, offering an alternative perspective on Apple’s valuation using comparable companies within the technology sector.
B23: EV/ Revenue | C23: =O6*T16 -> 3897383.5 | D23: =J6 -> 45192 | E23: =C23-D23 -> 3852191.5 | F23: =F6 -> 14920 | G23: =E23/F23 -> 258.18978 | H23: =E6 -> 250.12 | I23: Implied SP > SP | J23: Undervalued
B24: EV/ EBITDA | C24: =P6*W16 -> 3123594.8 | D24: =J6 -> 45192 | E24: =C24-D24 -> 3078402.8 | F24: =F6 -> 14920 | G24: =E24/F24 -> 206.32727 | H24: =E6 -> 250.12 | I24: Implied SP < SP | J24: Overvalued
B25: P/B | E25: =L6*U16 -> 724461.83 | F25: =F24 -> 14920 | G25: =E25/F6 -> 48.556423 | H25: =H24 -> 250.12 | I25: =I24 -> Implied SP < SP | J25: Overvalued
B26: P/E | E26: =Q6*V16 -> 3179260.8 | F26: =F25 -> 14920 | G26: =E26/F26 -> 213.08719 | H26: =H25 -> 250.12 | I26: =I25 -> Implied SP < SP | J26: =J25 -> Overvalued
B28: Target Price Calculation | E28: Note
B29: Metric | C29: Value | E29: Analysts normally remove weak multiples and give a valuation range. For tech companies like Apple Inc. the most reliable multiples are: • EV / EBITDA • P/E P/B is rarely used for tech because book value doesn't capture intangible assets.
B30: Low Target Price | C30: =G24 -> 206.32727
B31: High Target Price | C31: =G26 -> 213.08719
B32: Base Target Price | C32: =AVERAGE(C30:C31) -> 209.70723
B34: Final Valuation Summary
B35: Current Price | C35: =H23 -> 250.12
B36: Target Price | C36: =C32 -> 209.70723
B37: Upside / Downside | C37: =(C36-C35)/C35 -> -0.16157354
B38: Conclusion | C38: Overvalued
B41: Comparables Multiples Chart
B42: Ticker | C42: EV/ Revenue | D42: P/B | E42: P/E | F42: EV/ EBITDA
B43: AAPL | C43: 8.6704201 | D43: 42.315346 | E43: 31.620733 | F43: 24.701982
B44: GOOG | C44: 9.2232045 | D44: 8.8783206 | E44: 27.861368 | F44: 24.740728
B45: MSFT | C45: 9.7720602 | D45: 7.5512481 | E45: 24.737336 | F45: 16.155493
B46: META | C46: 8.0994474 | D46: 7.2715325 | E46: 26.126437 | F46: 15.97489
B62: The comparable multiples chart illustrates how Apple’s valuation compares with its industry peers. The comparison across EV/Revenue, EV/EBITDA, and P/E ratios helps identify whether Apple is trading at a premium or discount relative to similar technology companies. Differences in multiples reflect variations in growth expectations, profitability, and market sentiment across the peer group.

Sheet Football Field Analysis
K3: Football Field Analysis For Apple Inc
K5: Football Field Analysis
K6: Method | L6: Start | M6: Low | N6: High | O6: Range | P6: Current Price | Q6: Data Input
K7: Comps | L7: =M7 -> 206.32727 | M7: ='Relative Valuation'!C30 -> 206.32727 | N7: ='Relative Valuation'!C31 -> 213.08719 | O7: =N7-M7 -> 6.7599204 | P7: 250.12 | Q7: From Relative Valuation
K8: DCF Bear | L8: =M8 -> 87.865242 | M8: ='Sensitivity Analysis'!C38 -> 87.865242 | N8: ='Sensitivity Analysis'!E37 -> 109.80298 | O8: =N8-M8 -> 21.937738 | P8: 250.12 | Q8: From DCF Valuation Sensitivity Analysis
K9: DCF Base | L9: =M9 -> 98.703512 | M9: ='Sensitivity Analysis'!C37 -> 98.703512 | N9: 120 | O9: =N9-M9 -> 21.296488 | P9: 250.12 | Q9: From DCF Valuation Sensitivity Analysis
K10: DCF Bull | L10: =M10 -> 112.84265 | M10: ='Sensitivity Analysis'!C36 -> 112.84265 | N10: ='Sensitivity Analysis'!E36 -> 128.19256 | O10: =N10-M10 -> 15.349903 | P10: 250.12 | Q10: From DCF Valuation Sensitivity Analysis
K11: 52W H/L | L11: =M11 -> 169.21 | M11: 169.21 | N11: 288.62 | O11: =N11-M11 -> 119.41 | P11: 250.12 | Q11: Market Data From Stock Analysis.Com
S13: Interpretation: The football field analysis compares valuation ranges derived from DCF scenarios, comparable company multiples, and the stock’s historical trading range. The current market price of $250 lies significantly above the DCF valuation range ($88–$128), suggesting the stock may be overvalued under conservative cash flow assumptions. However, the comparable company analysis yields a higher valuation range ($206–$213), indicating the market may be pricing the firm based on relative industry multiples rather than intrinsic valuation.

Sheet Conclusion
B3: Limitations of the Model: • DCF is sensitive to WACC assumptions • Terminal value accounts for majority of valuation • Market sentiment may cause temporary mispricing • Relative valuation depends on peer selection While the valuation model provides a structured estimate of Apple’s intrinsic value, it is sensitive to key assumptions such as discount rates and long-term growth expectations. Additionally, terminal value contributes a large portion of total valuation, making long-term assumptions particularly important. Therefore, valuation results should be interpreted as indicative estimates rather than precise predictions.
B16: Conclusion: This valuation project aimed to estimate the intrinsic value of Apple Inc. using both Discounted Cash Flow (DCF) and Relative Valuation methods. The DCF model was developed by forecasting Apple’s future free cash flows based on assumptions regarding revenue growth, operating margins, capital expenditures, and working capital requirements. These projected cash flows were then discounted using the company’s Weighted Average Cost of Capital (WACC) to determine the present value of the firm. The results from the DCF model indicate an intrinsic value per share that is significantly lower than Apple’s current market price. Sensitivity analysis further demonstrated that the valuation is particularly influenced by changes in the discount rate and terminal growth assumptions, highlighting the importance of long-term growth expectations in determining firm value. In addition to the DCF approach, a Comparable Company Analysis was conducted using key valuation multiples such as EV/Revenue, EV/EBITDA, Price-to-Earnings (P/E), and Price-to-Book (P/B). By comparing Apple with major technology peers including Microsoft, Alphabet, and Meta, the relative valuation provided an alternative market-based estimate of Apple’s equity value. The results from this method suggest a valuation range that is closer to, but still generally below, the current market price. Overall, the analysis indicates that Apple’s stock appears to be trading at a premium relative to its fundamental valuation estimates. This premium may reflect strong investor confidence in the company’s long-term growth potential, innovation capabilities, and dominant ecosystem within the technology industry. While valuation models provide structured estimates of intrinsic value, actual market prices are also influenced by market sentiment, expectations of future technological developments, and macroeconomic conditions. In conclusion, the valuation exercise demonstrates how both intrinsic valuation techniques and market-based comparisons can be used together to assess a company’s fair value and support informed investment decision-making.
